subdomain/__init__.py
subdomain/__main__.py
subdomain/dict/default.txt
subdomain/dict/test.txt
subdomain/subdomain.py
subdomain-0.1.4.11.dist-info/WHEEL
subdomain-0.1.4.11.dist-info/METADATA
subdomain-0.1.4.11.dist-info/RECORD
